yapsl/__init__.py
yapsl/encoding.py
yapsl/sms_gateway.py
yapsl-0.1.4.dist-info/WHEEL
yapsl-0.1.4.dist-info/METADATA
yapsl-0.1.4.dist-info/RECORD
