Metadata-Version: 2.1
Name: yapsl
Version: 0.1.4
Summary: 
Home-page: https://github.com/kutoga/yapsl
Author: Benjamin Bruno Meier
Author-email: benjamin.meier70@gmail.com
Requires-Python: >=3.10,<4.0
Classifier: Programming Language :: Python :: 3
Classifier: Programming Language :: Python :: 3.10
Requires-Dist: alog (>=1.2.0,<2.0.0)
